[
  {
    "start": 3.99,
    "end": 11.08,
    "speaker": "老师",
    "text": "嗯嗯，"
  },
  {
    "start": 11.08,
    "end": 12.14,
    "speaker": "老师",
    "text": "亲爱的同学们，"
  },
  {
    "start": 12.14,
    "end": 13.46,
    "speaker": "老师",
    "text": "你们好。"
  },
  {
    "start": 13.46,
    "end": 15.54,
    "speaker": "老师",
    "text": "在第十八章的学习当中，"
  },
  {
    "start": 15.56,
    "end": 19.62,
    "speaker": "老师",
    "text": "我们对平行四边形呢进行了深入的研究。"
  },
  {
    "start": 19.62,
    "end": 20.52,
    "speaker": "老师",
    "text": "不仅如此，"
  },
  {
    "start": 21.02,
    "end": 27.98,
    "speaker": "老师",
    "text": "我们还知道了有一个角是直角的平行四边形是矩形，"
  },
  {
    "start": 28.06,
    "end": 32.5,
    "speaker": "老师",
    "text": "而有一组邻边相等的平行四边形呢是矩形。"
  },
  {
    "start": 32.5,
    "end": 48.82,
    "speaker": "老师",
    "text": "那么首先呢我们一起回顾一下从平行四边形到矩形和菱形的变化过程。"
  },
  {
    "start": 48.82,
    "end": 49.16,
    "speaker": "老师",
    "text": "好，"
  },
  {
    "start": 49.16,
    "end": 57.38,
    "speaker": "老师",
    "text": "同学们请看从平行四边形到矩行是角度在变化，"
  },
  {
    "start": 57.38,
    "end": 61.54,
    "speaker": "老师",
    "text": "一个角呢变成了直角。"
  },
  {
    "start": 61.54,
    "end": 61.82,
    "speaker": "老师",
    "text": "好，"
  },
  {
    "start": 61.82,
    "end": 64.92,
    "speaker": "老师",
    "text": "我们将它还原。"
  },
  {
    "start": 64.96,
    "end": 68.86,
    "speaker": "老师",
    "text": "那么从平行四边形到菱形呢，"
  },
  {
    "start": 68.86,
    "end": 72.36,
    "speaker": "老师",
    "text": "哎是边的长度发生了变化，"
  },
  {
    "start": 72.44,
    "end": 76.14,
    "speaker": "老师",
    "text": "有一组邻边变得相等了。"
  },
  {
    "start": 76.14,
    "end": 76.56,
    "speaker": "老师",
    "text": "好，"
  },
  {
    "start": 76.56,
    "end": 79.18,
    "speaker": "老师",
    "text": "我们再一次将图形还原。"
  },
  {
    "start": 79.4,
    "end": 82.06,
    "speaker": "老师",
    "text": "如果说一个平行四边形，"
  },
  {
    "start": 82.06,
    "end": 85.44,
    "speaker": "老师",
    "text": "我既要使它的一个角变为直角，"
  },
  {
    "start": 85.44,
    "end": 95.54,
    "speaker": "老师",
    "text": "又要使它的一组邻边变得相等，"
  },
  {
    "start": 95.54,
    "end": 98.74,
    "speaker": "老师",
    "text": "那么会得到一个怎样的图形呢？"
  },
  {
    "start": 98.76,
    "end": 102.58,
    "speaker": "老师",
    "text": "我们一起来看一看好了同学们，"
  },
  {
    "start": 102.58,
    "end": 104.98,
    "speaker": "老师",
    "text": "这个图形你们认识吗？"
  },
  {
    "start": 105.2,
    "end": 105.68,
    "speaker": "老师",
    "text": "没错，"
  },
  {
    "start": 105.68,
    "end": 111.12,
    "speaker": "老师",
    "text": "正方形相信大家呀对正方形应该已经非常熟悉了。"
  },
  {
    "start": 111.12,
    "end": 122.04,
    "speaker": "老师",
    "text": "但是我们以往的经验都是对正方形的感性认识。"
  },
  {
    "start": 122.04,
    "end": 127.6,
    "speaker": "老师",
    "text": "那么今天我们将从理性的角度来进一步剖析正方形。"
  },
  {
    "start": 127.6,
    "end": 128.8,
    "speaker": "老师",
    "text": "那么首先呢，"
  },
  {
    "start": 128.8,
    "end": 132.26,
    "speaker": "老师",
    "text": "我们应该对这个图形进行定义。"
  },
  {
    "start": 132.26,
    "end": 135.8,
    "speaker": "老师",
    "text": "根据刚才平行四边形的变化过程，"
  },
  {
    "start": 135.8,
    "end": 139.02,
    "speaker": "老师",
    "text": "我们知道一个平行四边形，"
  },
  {
    "start": 139.02,
    "end": 141.84,
    "speaker": "老师",
    "text": "它的一个角变成直角，"
  },
  {
    "start": 141.84,
    "end": 144.78,
    "speaker": "老师",
    "text": "一组邻边变得相等。"
  },
  {
    "start": 144.92,
    "end": 148.84,
    "speaker": "老师",
    "text": "那么我们就可以得到一个正方形。"
  },
  {
    "start": 148.84,
    "end": 153.67,
    "speaker": "老师",
    "text": "其实啊这也正是正方形的定义，"
  },
  {
    "start": 153.67,
    "end": 155.31,
    "speaker": "老师",
    "text": "有一组邻边相等，"
  },
  {
    "start": 155.31,
    "end": 158.47,
    "speaker": "老师",
    "text": "并且有一个角是直角的平行四边形，"
  },
  {
    "start": 158.47,
    "end": 159.85,
    "speaker": "老师",
    "text": "就是正方形。"
  },
  {
    "start": 159.85,
    "end": 163.7,
    "speaker": "老师",
    "text": "那么在十八章的学习当中，"
  },
  {
    "start": 163.7,
    "end": 165.94,
    "speaker": "老师",
    "text": "我们学习了很多四边形，"
  },
  {
    "start": 165.94,
    "end": 171.92,
    "speaker": "老师",
    "text": "这些四边形之间又有一个怎样的关系呢？"
  },
  {
    "start": 172.1,
    "end": 174.14,
    "speaker": "老师",
    "text": "我们一起来看，"
  },
  {
    "start": 174.14,
    "end": 178.18,
    "speaker": "老师",
    "text": "在四边形的大家庭当中有一个图形，"
  },
  {
    "start": 178.18,
    "end": 180.4,
    "speaker": "老师",
    "text": "它比较特殊，"
  },
  {
    "start": 180.4,
    "end": 183.66,
    "speaker": "老师",
    "text": "它是两组对边分别平行的。"
  },
  {
    "start": 183.66,
    "end": 184.68,
    "speaker": "老师",
    "text": "没错，"
  },
  {
    "start": 184.72,
    "end": 187.04,
    "speaker": "老师",
    "text": "它是平行四边形之后呢，"
  },
  {
    "start": 187.04,
    "end": 191.76,
    "speaker": "老师",
    "text": "我们又认识了两种特殊的平行四边形，"
  },
  {
    "start": 191.76,
    "end": 193.62,
    "speaker": "老师",
    "text": "分别是矩形和菱形。"
  },
  {
    "start": 193.62,
    "end": 198.68,
    "speaker": "老师",
    "text": "那么矩形和菱形是没有交集，"
  },
  {
    "start": 198.7,
    "end": 204.93,
    "speaker": "老师",
    "text": "独立存在于平行四边形当中的吗？"
  },
  {
    "start": 204.93,
    "end": 208.09,
    "speaker": "老师",
    "text": "根据刚才的图形变化，"
  },
  {
    "start": 208.13,
    "end": 214.01,
    "speaker": "老师",
    "text": "我们发现呢有一种平行四边形它比较特殊，"
  },
  {
    "start": 214.05,
    "end": 217.82,
    "speaker": "老师",
    "text": "它既有一个角是直角，"
  },
  {
    "start": 217.82,
    "end": 219.74,
    "speaker": "老师",
    "text": "又有一组邻边相等，"
  },
  {
    "start": 219.74,
    "end": 221.46,
    "speaker": "老师",
    "text": "它就是正方形。"
  },
  {
    "start": 221.54,
    "end": 222.58,
    "speaker": "老师",
    "text": "由此可见，"
  },
  {
    "start": 222.58,
    "end": 227.14,
    "speaker": "老师",
    "text": "正方形它既是特殊的平行四边形，"
  },
  {
    "start": 227.14,
    "end": 230.6,
    "speaker": "老师",
    "text": "同时呢它也是特殊的矩形，"
  },
  {
    "start": 230.6,
    "end": 232.96,
    "speaker": "老师",
    "text": "还是特殊的菱形。"
  },
  {
    "start": 232.96,
    "end": 255.53,
    "speaker": "老师",
    "text": "所以正方形它应该不仅具有平行四边形的性质，"
  },
  {
    "start": 255.53,
    "end": 258.64,
    "speaker": "老师",
    "text": "矩形和菱形的性质呢它也都有。"
  },
  {
    "start": 258.64,
    "end": 262.6,
    "speaker": "老师",
    "text": "那么正方形到底具有哪些性质呢？"
  },
  {
    "start": 262.6,
    "end": 268.88,
    "speaker": "老师",
    "text": "现在呀先请同学们自己归纳总结一下。"
  },
  {
    "start": 268.88,
    "end": 269.42,
    "speaker": "老师",
    "text": "好了，"
  },
  {
    "start": 269.58,
    "end": 270.68,
    "speaker": "老师",
    "text": "同学们，"
  },
  {
    "start": 270.68,
    "end": 276.44,
    "speaker": "老师",
    "text": "我们应该从哪几个方面来归纳正方形的性质呢？"
  },
  {
    "start": 276.6,
    "end": 277.2,
    "speaker": "老师",
    "text": "没错，"
  },
  {
    "start": 277.38,
    "end": 282.28,
    "speaker": "老师",
    "text": "经过了平行四边形矩形和菱形的学习，"
  },
  {
    "start": 282.28,
    "end": 293.16,
    "speaker": "老师",
    "text": "相信啊大家应该会从边角对角线以及图形的对称性四个方面来总结正方形的性质。"
  },
  {
    "start": 293.16,
    "end": 297.35,
    "speaker": "老师",
    "text": "首先正方形的边在位置上，"
  },
  {
    "start": 297.35,
    "end": 302.82,
    "speaker": "老师",
    "text": "正方形的边应该是两组对边分别平行的关系。"
  },
  {
    "start": 302.92,
    "end": 309.8,
    "speaker": "老师",
    "text": "同时呢在数量上它应该与菱形一样四条边都相等。"
  },
  {
    "start": 309.8,
    "end": 311.72,
    "speaker": "老师",
    "text": "那正方形的角呢？"
  },
  {
    "start": 312.14,
    "end": 313.14,
    "speaker": "老师",
    "text": "没错，"
  },
  {
    "start": 313.14,
    "end": 316.16,
    "speaker": "老师",
    "text": "它应该与矩形的角相同，"
  },
  {
    "start": 316.2,
    "end": 319.6,
    "speaker": "老师",
    "text": "四个角都是直角。"
  },
  {
    "start": 319.78,
    "end": 322.58,
    "speaker": "老师",
    "text": "那关于正方形的对角线呢，"
  },
  {
    "start": 322.58,
    "end": 324.94,
    "speaker": "老师",
    "text": "数量上它应该与矩形相同，"
  },
  {
    "start": 324.94,
    "end": 327.62,
    "speaker": "老师",
    "text": "两条对角线相等。"
  },
  {
    "start": 327.62,
    "end": 331.84,
    "speaker": "老师",
    "text": "而在位置上它又与菱形相同，"
  },
  {
    "start": 331.86,
    "end": 333.26,
    "speaker": "老师",
    "text": "不仅互相平分，"
  },
  {
    "start": 333.76,
    "end": 336.18,
    "speaker": "老师",
    "text": "而且呀还是垂直的关系。"
  },
  {
    "start": 336.18,
    "end": 341.74,
    "speaker": "老师",
    "text": "同时还有每一条对角线平分了一组对角。"
  },
  {
    "start": 341.74,
    "end": 345.4,
    "speaker": "老师",
    "text": "最后正方形它是轴对称图形吗？"
  },
  {
    "start": 345.4,
    "end": 352.34,
    "speaker": "老师",
    "text": "同学们可以自己拿出一张正方形的纸片来折一折。"
  },
  {
    "start": 352.34,
    "end": 357.86,
    "speaker": "老师",
    "text": "我们发现沿着正方形的两条对角线将正方形进行折叠，"
  },
  {
    "start": 357.86,
    "end": 360.26,
    "speaker": "老师",
    "text": "会发现两个部分呢完全重合。"
  },
  {
    "start": 360.26,
    "end": 367.16,
    "speaker": "老师",
    "text": "另外如果沿着正方形对边中点所在的直线将正方形折叠呢，"
  },
  {
    "start": 367.16,
    "end": 370.91,
    "speaker": "老师",
    "text": "哎两部分也是会重合的。"
  },
  {
    "start": 370.91,
    "end": 375.39,
    "speaker": "老师",
    "text": "因此我们可以得出正方形一共有四条对称轴。"
  },
  {
    "start": 375.39,
    "end": 375.93,
    "speaker": "老师",
    "text": "好了，"
  },
  {
    "start": 375.95,
    "end": 376.95,
    "speaker": "老师",
    "text": "同学们，"
  },
  {
    "start": 376.95,
    "end": 382.91,
    "speaker": "老师",
    "text": "那么你们对正方形的性质是不是已经有所了解了呢？"
  },
  {
    "start": 382.93,
    "end": 385.93,
    "speaker": "老师",
    "text": "那接下来呀老师要来考考大家，"
  },
  {
    "start": 385.93,
    "end": 394.67,
    "speaker": "老师",
    "text": "大家请看正方形具有而矩形不一定具有的性质是首先a选项四个角相等。"
  },
  {
    "start": 395.21,
    "end": 395.73,
    "speaker": "老师",
    "text": "哎，"
  },
  {
    "start": 395.75,
    "end": 400.53,
    "speaker": "老师",
    "text": "我们知道正方形的角与矩形的角应该是一样的，"
  },
  {
    "start": 400.55,
    "end": 402.89,
    "speaker": "老师",
    "text": "四个角呢都是九十度，"
  },
  {
    "start": 402.89,
    "end": 407.21,
    "speaker": "老师",
    "text": "因此四个角都相等没有问题。"
  },
  {
    "start": 407.21,
    "end": 407.43,
    "speaker": "老师",
    "text": "好，"
  },
  {
    "start": 407.43,
    "end": 411.57,
    "speaker": "老师",
    "text": "b选项对角线互相垂直平分。"
  },
  {
    "start": 411.79,
    "end": 412.29,
    "speaker": "老师",
    "text": "好，"
  },
  {
    "start": 412.29,
    "end": 418.89,
    "speaker": "老师",
    "text": "那我们来回忆一下矩形的对角线有哪些性质呢？"
  },
  {
    "start": 419.11,
    "end": 421.79,
    "speaker": "老师",
    "text": "首先应该是对角线相等，"
  },
  {
    "start": 421.79,
    "end": 425.86,
    "speaker": "老师",
    "text": "另外呢对角线还会互相平分。"
  },
  {
    "start": 425.86,
    "end": 428.48,
    "speaker": "老师",
    "text": "而正方形的对角线呢，"
  },
  {
    "start": 428.48,
    "end": 432.96,
    "speaker": "老师",
    "text": "刚才我们列出了很多因哪些在数量上，"
  },
  {
    "start": 432.96,
    "end": 436.93,
    "speaker": "老师",
    "text": "它应该是两条对角线相等。"
  },
  {
    "start": 436.99,
    "end": 441.38,
    "speaker": "老师",
    "text": "而在位置上呢哎正方形的对角线是互相垂直平分，"
  },
  {
    "start": 442.0,
    "end": 445.26,
    "speaker": "老师",
    "text": "并且还有每一条对角线平分一组对角。"
  },
  {
    "start": 445.26,
    "end": 448.72,
    "speaker": "老师",
    "text": "因此啊这里的垂直应该是正方形，"
  },
  {
    "start": 448.8,
    "end": 451.76,
    "speaker": "老师",
    "text": "具有而矩形不具有的性质。"
  },
  {
    "start": 451.76,
    "end": 452.12,
    "speaker": "老师",
    "text": "好，"
  },
  {
    "start": 452.12,
    "end": 454.12,
    "speaker": "老师",
    "text": "继续我们往后看c选项，"
  },
  {
    "start": 455.04,
    "end": 456.2,
    "speaker": "老师",
    "text": "对角互补。"
  },
  {
    "start": 456.2,
    "end": 458.92,
    "speaker": "老师",
    "text": "我们在学习平行四边形的时候，"
  },
  {
    "start": 458.92,
    "end": 463.52,
    "speaker": "老师",
    "text": "知道平行四边形的棱角应该是互补的，"
  },
  {
    "start": 463.52,
    "end": 467.74,
    "speaker": "老师",
    "text": "而正方形和矩形的四个角都是九十度，"
  },
  {
    "start": 467.74,
    "end": 471.14,
    "speaker": "老师",
    "text": "也就是每个角都是九十度。"
  },
  {
    "start": 471.14,
    "end": 474.1,
    "speaker": "老师",
    "text": "那么对角是不是相加为一百八，"
  },
  {
    "start": 474.1,
    "end": 493.46,
    "speaker": "老师",
    "text": "那我说对角互补也是没有问题的。"
  },
  {
    "start": 493.46,
    "end": 494.16,
    "speaker": "老师",
    "text": "好，"
  },
  {
    "start": 494.16,
    "end": 496.58,
    "speaker": "老师",
    "text": "最后一个d选项，"
  },
  {
    "start": 496.6,
    "end": 497.94,
    "speaker": "老师",
    "text": "对角线相等。"
  },
  {
    "start": 497.94,
    "end": 502.58,
    "speaker": "老师",
    "text": "刚才我们呢已经回忆过对角线的性质了，"
  },
  {
    "start": 502.58,
    "end": 507.52,
    "speaker": "老师",
    "text": "正方形和矩形的对角心连线呢应该都是相等的。"
  },
  {
    "start": 507.68,
    "end": 511.68,
    "speaker": "老师",
    "text": "因此这道题目我们选择的是b选项。"
  },
  {
    "start": 511.68,
    "end": 512.02,
    "speaker": "老师",
    "text": "好，"
  },
  {
    "start": 512.02,
    "end": 517.44,
    "speaker": "老师",
    "text": "接下来呢我们再来看这道题目，"
  },
  {
    "start": 517.44,
    "end": 520.76,
    "speaker": "老师",
    "text": "一个正方形的对角线长为两厘米，"
  },
  {
    "start": 520.86,
    "end": 523.48,
    "speaker": "老师",
    "text": "则它的面积是多少呢？"
  },
  {
    "start": 523.48,
    "end": 527.62,
    "speaker": "老师",
    "text": "先请同学们呢自己计算好了。"
  },
  {
    "start": 527.64,
    "end": 540.14,
    "speaker": "老师",
    "text": "同学们是不是已经有同学在根据对角线的长来求得正方形的边长之后呢，"
  },
  {
    "start": 540.14,
    "end": 542.42,
    "speaker": "老师",
    "text": "再来求正方形的面积呢？"
  },
  {
    "start": 542.42,
    "end": 543.68,
    "speaker": "老师",
    "text": "好，"
  },
  {
    "start": 543.68,
    "end": 546.06,
    "speaker": "老师",
    "text": "这个方法呀非常好。"
  },
  {
    "start": 546.06,
    "end": 548.44,
    "speaker": "老师",
    "text": "那还有其殊的方法吗？"
  },
  {
    "start": 548.52,
    "end": 553.1,
    "speaker": "老师",
    "text": "我们说正方形它是特殊的平行四边形，"
  },
  {
    "start": 553.1,
    "end": 556.2,
    "speaker": "老师",
    "text": "同时呢它也是特殊的矩形，"
  },
  {
    "start": 556.2,
    "end": 558.64,
    "speaker": "老师",
    "text": "还是特殊的菱形。"
  },
  {
    "start": 558.78,
    "end": 576.69,
    "speaker": "老师",
    "text": "而菱形的面积我们可以用对角线的积除以二来进行计算。"
  },
  {
    "start": 576.69,
    "end": 578.53,
    "speaker": "老师",
    "text": "对于正方形来说，"
  },
  {
    "start": 578.53,
    "end": 581.31,
    "speaker": "老师",
    "text": "两条对角线相等，"
  },
  {
    "start": 581.31,
    "end": 591.56,
    "speaker": "老师",
    "text": "因此啊它的面积也可以用二乘以二，"
  },
  {
    "start": 591.56,
    "end": 594.26,
    "speaker": "老师",
    "text": "再乘以二分之一，"
  },
  {
    "start": 594.64,
    "end": 598.8,
    "speaker": "老师",
    "text": "可以得出应该选择a好，"
  },
  {
    "start": 598.9,
    "end": 605.2,
    "speaker": "老师",
    "text": "接下来呢我们再来看一道几何证明题，"
  },
  {
    "start": 605.98,
    "end": 608.18,
    "speaker": "老师",
    "text": "求证正方形的两条对角线，"
  },
  {
    "start": 608.18,
    "end": 614.2,
    "speaker": "老师",
    "text": "把这个正方形分成了四个全等的等腰直角三角形。"
  },
  {
    "start": 614.2,
    "end": 614.5,
    "speaker": "老师",
    "text": "好，"
  },
  {
    "start": 614.5,
    "end": 615.82,
    "speaker": "老师",
    "text": "这道题目啊，"
  },
  {
    "start": 615.82,
    "end": 621.26,
    "speaker": "老师",
    "text": "请同学们先自己将文字语言转化为已知求证，"
  },
  {
    "start": 621.3,
    "end": 623.42,
    "speaker": "老师",
    "text": "画出图形，"
  },
  {
    "start": 623.66,
    "end": 624.98,
    "speaker": "老师",
    "text": "并且呀进行证明。"
  },
  {
    "start": 624.98,
    "end": 625.62,
    "speaker": "老师",
    "text": "好了，"
  },
  {
    "start": 625.72,
    "end": 626.38,
    "speaker": "老师",
    "text": "同学们，"
  },
  {
    "start": 626.38,
    "end": 628.42,
    "speaker": "老师",
    "text": "我们一起来看一看，"
  },
  {
    "start": 628.42,
    "end": 632.78,
    "speaker": "老师",
    "text": "老师是如何把文字语言转化为数学语言的。"
  },
  {
    "start": 632.78,
    "end": 634.57,
    "speaker": "老师",
    "text": "已知如图，"
  },
  {
    "start": 634.57,
    "end": 636.59,
    "speaker": "老师",
    "text": "四边形ABCD是正方形，"
  },
  {
    "start": 636.59,
    "end": 647.09,
    "speaker": "老师",
    "text": "对角线呢相交于点o求证三角形ABO、三角形BCO、三角形CDO和三角形DAO是全等的等腰直角三角形。"
  },
  {
    "start": 647.25,
    "end": 647.57,
    "speaker": "老师",
    "text": "好，"
  },
  {
    "start": 647.57,
    "end": 651.06,
    "speaker": "老师",
    "text": "面对着这样的一个几何证明题，"
  },
  {
    "start": 651.1,
    "end": 653.88,
    "speaker": "老师",
    "text": "我们要么从已知入手，"
  },
  {
    "start": 654.1,
    "end": 656.4,
    "speaker": "老师",
    "text": "要么从求证入手，"
  },
  {
    "start": 656.42,
    "end": 659.9,
    "speaker": "老师",
    "text": "要么呢把这两者往中间凑一凑。"
  },
  {
    "start": 659.9,
    "end": 662.92,
    "speaker": "老师",
    "text": "那么我们先来看这道题目的，"
  },
  {
    "start": 662.92,
    "end": 664.08,
    "speaker": "老师",
    "text": "已知如图，"
  },
  {
    "start": 664.08,
    "end": 667.16,
    "speaker": "老师",
    "text": "四边形ABCD是正方形，"
  },
  {
    "start": 668.09,
    "end": 672.91,
    "speaker": "老师",
    "text": "并且呀还给我们把对角线画出来了，"
  },
  {
    "start": 672.97,
    "end": 681.69,
    "speaker": "老师",
    "text": "相交于点o我们是不是应该把正方形所有的性质全部在图形上进行标出呢？"
  },
  {
    "start": 681.69,
    "end": 686.59,
    "speaker": "老师",
    "text": "我们已经知道正方形的性质啊它比较多。"
  },
  {
    "start": 686.59,
    "end": 689.45,
    "speaker": "老师",
    "text": "如果我把所有的性质全部标出来，"
  },
  {
    "start": 689.45,
    "end": 693.77,
    "speaker": "老师",
    "text": "那么整个图形呢就会显得非常的乱。"
  },
  {
    "start": 693.87,
    "end": 699.29,
    "speaker": "老师",
    "text": "而且我不知道哪一条性质应该是有用的，"
  },
  {
    "start": 699.31,
    "end": 702.91,
    "speaker": "老师",
    "text": "这样啊思路就不会清晰。"
  },
  {
    "start": 703.11,
    "end": 705.55,
    "speaker": "老师",
    "text": "那我们换一个角度，"
  },
  {
    "start": 705.71,
    "end": 711.38,
    "speaker": "老师",
    "text": "如果从求证入手呢，"
  },
  {
    "start": 711.38,
    "end": 718.68,
    "speaker": "老师",
    "text": "同学们请看求证这四个三角形是全等的等腰直角三角形。"
  },
  {
    "start": 718.68,
    "end": 724.38,
    "speaker": "老师",
    "text": "那么其实这道题目让我们证明的是两个结论。"
  },
  {
    "start": 724.38,
    "end": 724.82,
    "speaker": "老师",
    "text": "第一，"
  },
  {
    "start": 724.82,
    "end": 728.35,
    "speaker": "老师",
    "text": "这四个三角形是全等的关系。"
  },
  {
    "start": 728.35,
    "end": 728.89,
    "speaker": "老师",
    "text": "第二，"
  },
  {
    "start": 728.89,
    "end": 731.81,
    "speaker": "老师",
    "text": "它们呢还都是等腰直角三角形。"
  },
  {
    "start": 731.81,
    "end": 732.39,
    "speaker": "老师",
    "text": "好，"
  },
  {
    "start": 732.47,
    "end": 735.27,
    "speaker": "老师",
    "text": "我们结合求证内容以及图形，"
  },
  {
    "start": 735.27,
    "end": 743.43,
    "speaker": "老师",
    "text": "我们看一看这四个三角形的位置在哪里呢？"
  },
  {
    "start": 743.53,
    "end": 743.89,
    "speaker": "老师",
    "text": "好，"
  },
  {
    "start": 743.89,
    "end": 746.17,
    "speaker": "老师",
    "text": "现在呀我们先做一个预判，"
  },
  {
    "start": 746.33,
    "end": 749.21,
    "speaker": "老师",
    "text": "它说的等腰直角三角形，"
  },
  {
    "start": 749.49,
    "end": 759.27,
    "speaker": "老师",
    "text": "这四个等腰直角三角形的直角应该是哪个角呢？"
  },
  {
    "start": 759.29,
    "end": 760.17,
    "speaker": "老师",
    "text": "没错，"
  },
  {
    "start": 760.69,
    "end": 764.17,
    "speaker": "老师",
    "text": "应该呀都是以点o为顶点的这个角。"
  },
  {
    "start": 764.17,
    "end": 768.34,
    "speaker": "老师",
    "text": "那么要证明这四个三角形是直角三角形，"
  },
  {
    "start": 768.34,
    "end": 773.26,
    "speaker": "老师",
    "text": "是不是也就是证明AC与BD垂直呢？"
  },
  {
    "start": 773.26,
    "end": 773.64,
    "speaker": "老师",
    "text": "好，"
  },
  {
    "start": 773.94,
    "end": 782.24,
    "speaker": "老师",
    "text": "那么这也正是题目当中ABCD这个正方形的对角线呢，"
  },
  {
    "start": 782.26,
    "end": 787.36,
    "speaker": "老师",
    "text": "而我们知道正方形的对角线就是互相垂直的。"
  },
  {
    "start": 787.36,
    "end": 802.27,
    "speaker": "老师",
    "text": "所以直角我们直接可以通过对角线的性质进行证明。"
  },
  {
    "start": 802.27,
    "end": 807.91,
    "speaker": "老师",
    "text": "好再来进一步看一看它不仅是直角三角形还是等腰直角三角形，"
  },
  {
    "start": 807.93,
    "end": 812.11,
    "speaker": "老师",
    "text": "也就意味着我们要证明OA等于OB,"
  },
  {
    "start": 812.11,
    "end": 814.51,
    "speaker": "老师",
    "text": "还等于OC等于OD."
  },
  {
    "start": 814.57,
    "end": 817.43,
    "speaker": "老师",
    "text": "我们知道正方形的对角线呢，"
  },
  {
    "start": 817.43,
    "end": 819.31,
    "speaker": "老师",
    "text": "它不仅互相垂直，"
  },
  {
    "start": 819.31,
    "end": 822.85,
    "speaker": "老师",
    "text": "而且还会怎么样互相平分，"
  },
  {
    "start": 823.01,
    "end": 826.59,
    "speaker": "老师",
    "text": "并且数量上两条对角线是相等的，"
  },
  {
    "start": 826.59,
    "end": 831.55,
    "speaker": "老师",
    "text": "因此OAOBOCOD不就相等了吗？"
  },
  {
    "start": 831.55,
    "end": 831.79,
    "speaker": "老师",
    "text": "哎，"
  },
  {
    "start": 831.79,
    "end": 838.21,
    "speaker": "老师",
    "text": "那么这一条结论我们呢就可以直接运用对角线的性质证明出来了，"
  },
  {
    "start": 838.27,
    "end": 845.9,
    "speaker": "老师",
    "text": "还要证明四个三角形是全等的。"
  },
  {
    "start": 845.9,
    "end": 847.14,
    "speaker": "老师",
    "text": "我们再来观察图形，"
  },
  {
    "start": 847.14,
    "end": 852.16,
    "speaker": "老师",
    "text": "我们发现这四个三角形有相等的直角边，"
  },
  {
    "start": 852.16,
    "end": 854.78,
    "speaker": "老师",
    "text": "并且所夹的角都是直角。"
  },
  {
    "start": 854.84,
    "end": 860.1,
    "speaker": "老师",
    "text": "那么这四个三角形是不是也就是全等的关系呢？"
  },
  {
    "start": 860.2,
    "end": 860.6,
    "speaker": "老师",
    "text": "好，"
  },
  {
    "start": 860.6,
    "end": 866.66,
    "speaker": "老师",
    "text": "那么接下来我们再一起回顾一下整道题目的证明思路。"
  },
  {
    "start": 866.66,
    "end": 867.56,
    "speaker": "老师",
    "text": "好了，"
  },
  {
    "start": 867.56,
    "end": 871.06,
    "speaker": "老师",
    "text": "同学们根据刚才的证明呢，"
  },
  {
    "start": 871.06,
    "end": 876.36,
    "speaker": "老师",
    "text": "我们知道了这四个小三角形啊都是等腰直角三角形。"
  },
  {
    "start": 876.38,
    "end": 878.52,
    "speaker": "老师",
    "text": "那么在这幅图形当中，"
  },
  {
    "start": 878.52,
    "end": 880.3,
    "speaker": "老师",
    "text": "除了这四个小三角形之外，"
  },
  {
    "start": 880.3,
    "end": 882.94,
    "speaker": "老师",
    "text": "还有等腰直角三角形吗？"
  },
  {
    "start": 882.94,
    "end": 887.5,
    "speaker": "老师",
    "text": "它一共又有多少个等腰直角三角形呢？"
  },
  {
    "start": 887.64,
    "end": 888.74,
    "speaker": "老师",
    "text": "我们不难发现，"
  },
  {
    "start": 888.74,
    "end": 892.04,
    "speaker": "老师",
    "text": "每两个等腰直角三角形放在一起，"
  },
  {
    "start": 892.04,
    "end": 897.73,
    "speaker": "老师",
    "text": "其实呢它可以组成一个大的等腰直角三角形。"
  },
  {
    "start": 897.73,
    "end": 909.97,
    "speaker": "老师",
    "text": "那么这样的三角形呢我们一共可以画出四个来。"
  },
  {
    "start": 909.97,
    "end": 915.89,
    "speaker": "老师",
    "text": "所以呀这幅图当中一共有八个等腰直角三角形。"
  },
  {
    "start": 915.89,
    "end": 916.35,
    "speaker": "老师",
    "text": "好了，"
  },
  {
    "start": 916.35,
    "end": 917.01,
    "speaker": "老师",
    "text": "同学们，"
  },
  {
    "start": 917.25,
    "end": 921.67,
    "speaker": "老师",
    "text": "那么对于一个图形的研究呢，"
  },
  {
    "start": 921.67,
    "end": 924.59,
    "speaker": "老师",
    "text": "我们先从定义和性质开始，"
  },
  {
    "start": 924.77,
    "end": 928.65,
    "speaker": "老师",
    "text": "接下来就应该到哪个环节了呢？"
  },
  {
    "start": 928.65,
    "end": 929.05,
    "speaker": "老师",
    "text": "没错，"
  },
  {
    "start": 929.05,
    "end": 933.0,
    "speaker": "老师",
    "text": "正方形的判定大家思考一下，"
  },
  {
    "start": 933.0,
    "end": 937.22,
    "speaker": "老师",
    "text": "我们应该如何对正方形进行判定呢？"
  },
  {
    "start": 937.46,
    "end": 938.08,
    "speaker": "老师",
    "text": "好，"
  },
  {
    "start": 938.22,
    "end": 941.1,
    "speaker": "老师",
    "text": "有同学肯定会说，"
  },
  {
    "start": 941.1,
    "end": 941.8,
    "speaker": "老师",
    "text": "老师，"
  },
  {
    "start": 941.8,
    "end": 948.19,
    "speaker": "老师",
    "text": "我知道我们呢可以从正方形性质的逆命题入手。"
  },
  {
    "start": 948.19,
    "end": 951.15,
    "speaker": "老师",
    "text": "如果你提出了这样的方案，"
  },
  {
    "start": 951.17,
    "end": 953.49,
    "speaker": "老师",
    "text": "那么恭喜你，"
  },
  {
    "start": 953.59,
    "end": 957.05,
    "speaker": "老师",
    "text": "你已经学会了类比学习。"
  },
  {
    "start": 957.13,
    "end": 961.97,
    "speaker": "老师",
    "text": "我们再进一步思考正方形的性质呢。"
  },
  {
    "start": 961.97,
    "end": 963.93,
    "speaker": "老师",
    "text": "刚才我们说了又非常的多。"
  },
  {
    "start": 963.93,
    "end": 970.06,
    "speaker": "老师",
    "text": "如果我们把每一条性质的逆命题写出来之后呢，"
  },
  {
    "start": 970.06,
    "end": 973.26,
    "speaker": "老师",
    "text": "再进行修改证明。"
  },
  {
    "start": 973.26,
    "end": 973.66,
    "speaker": "老师",
    "text": "哎，"
  },
  {
    "start": 973.66,
    "end": 978.82,
    "speaker": "老师",
    "text": "这样的工作量呢就会非常的大，"
  },
  {
    "start": 978.82,
    "end": 981.02,
    "speaker": "老师",
    "text": "而且非常的繁琐。"
  },
  {
    "start": 981.02,
    "end": 984.78,
    "speaker": "老师",
    "text": "那我们能不能从其他的角度来判定正方形呢？"
  },
  {
    "start": 984.78,
    "end": 987.36,
    "speaker": "老师",
    "text": "先给大家一点时间，"
  },
  {
    "start": 987.36,
    "end": 989.46,
    "speaker": "老师",
    "text": "同学们自己思考一下。"
  },
  {
    "start": 989.46,
    "end": 989.92,
    "speaker": "老师",
    "text": "好了，"
  },
  {
    "start": 990.24,
    "end": 997.6,
    "speaker": "老师",
    "text": "同学们其实啊我们还是要从图形之间的关系入手。"
  },
  {
    "start": 997.78,
    "end": 998.86,
    "speaker": "老师",
    "text": "根据这幅图形，"
  },
  {
    "start": 998.92,
    "end": 1003.38,
    "speaker": "老师",
    "text": "我们知道了正方形呢它是矩形和菱形重叠的这个部分。"
  },
  {
    "start": 1003.4,
    "end": 1004.4,
    "speaker": "老师",
    "text": "那换句话说，"
  },
  {
    "start": 1004.4,
    "end": 1008.58,
    "speaker": "老师",
    "text": "如果一个图形它既是矩形，"
  },
  {
    "start": 1008.6,
    "end": 1009.72,
    "speaker": "老师",
    "text": "又是菱形，"
  },
  {
    "start": 1009.74,
    "end": 1014.08,
    "speaker": "老师",
    "text": "那么这个图形是不是就是正方形了呢？"
  },
  {
    "start": 1014.12,
    "end": 1016.94,
    "speaker": "老师",
    "text": "所以呀面对一个几何图形，"
  },
  {
    "start": 1016.94,
    "end": 1021.56,
    "speaker": "老师",
    "text": "我们呢可以先判定它是矩形之后呢，"
  },
  {
    "start": 1021.56,
    "end": 1023.7,
    "speaker": "老师",
    "text": "再判定它又是菱形。"
  },
  {
    "start": 1023.82,
    "end": 1026.88,
    "speaker": "老师",
    "text": "那么这个图形它就是正方形。"
  },
  {
    "start": 1026.88,
    "end": 1031.0,
    "speaker": "老师",
    "text": "当然这个顺序呢我们还可以换一换，"
  },
  {
    "start": 1031.0,
    "end": 1033.1,
    "speaker": "老师",
    "text": "先判定它是菱形，"
  },
  {
    "start": 1033.14,
    "end": 1035.68,
    "speaker": "老师",
    "text": "再判定它是矩形。"
  },
  {
    "start": 1035.8,
    "end": 1040.3,
    "speaker": "老师",
    "text": "同样我们也可以判定这个图形是正方形。"
  },
  {
    "start": 1040.3,
    "end": 1047.16,
    "speaker": "老师",
    "text": "有的同学呢可能对老师刚才说的方法呀还比较陌生，"
  },
  {
    "start": 1047.16,
    "end": 1048.54,
    "speaker": "老师",
    "text": "没关系，"
  },
  {
    "start": 1048.54,
    "end": 1052.4,
    "speaker": "老师",
    "text": "我们可以边练习边巩固。"
  },
  {
    "start": 1052.92,
    "end": 1053.76,
    "speaker": "老师",
    "text": "同学们，"
  },
  {
    "start": 1053.76,
    "end": 1055.7,
    "speaker": "老师",
    "text": "请看下列命题。"
  },
  {
    "start": 1055.78,
    "end": 1057.38,
    "speaker": "老师",
    "text": "正确与否呢，"
  },
  {
    "start": 1057.46,
    "end": 1061.76,
    "speaker": "老师",
    "text": "第一个四个角都相等的四边形是正方形。"
  },
  {
    "start": 1061.98,
    "end": 1062.24,
    "speaker": "老师",
    "text": "哎，"
  },
  {
    "start": 1062.24,
    "end": 1069.24,
    "speaker": "老师",
    "text": "这个我们大家都知道四个角都相等的三四边形应该是每个角为九十度，"
  },
  {
    "start": 1069.68,
    "end": 1071.46,
    "speaker": "老师",
    "text": "一定是正方形吗？"
  },
  {
    "start": 1071.56,
    "end": 1072.24,
    "speaker": "老师",
    "text": "不对，"
  },
  {
    "start": 1072.8,
    "end": 1076.2,
    "speaker": "老师",
    "text": "它有可能是矩形。"
  },
  {
    "start": 1076.2,
    "end": 1076.62,
    "speaker": "老师",
    "text": "对了。"
  },
  {
    "start": 1076.62,
    "end": 1077.42,
    "speaker": "老师",
    "text": "好，"
  },
  {
    "start": 1077.64,
    "end": 1083.86,
    "speaker": "老师",
    "text": "第二个四条边都相等的四边形是正方形。"
  },
  {
    "start": 1083.86,
    "end": 1084.46,
    "speaker": "老师",
    "text": "哎，"
  },
  {
    "start": 1084.46,
    "end": 1085.9,
    "speaker": "老师",
    "text": "这个是什么呢？"
  },
  {
    "start": 1085.9,
    "end": 1087.94,
    "speaker": "老师",
    "text": "经过上一节课的学习，"
  },
  {
    "start": 1087.94,
    "end": 1092.12,
    "speaker": "老师",
    "text": "我们知道这应该是菱形的判定方法，"
  },
  {
    "start": 1092.12,
    "end": 1096.16,
    "speaker": "老师",
    "text": "因此第二个命题也是错误的。"
  },
  {
    "start": 1096.16,
    "end": 1101.52,
    "speaker": "老师",
    "text": "第三个对角线相等的平行四边形是正方形吗？"
  },
  {
    "start": 1101.62,
    "end": 1101.88,
    "speaker": "老师",
    "text": "哎，"
  },
  {
    "start": 1101.88,
    "end": 1107.65,
    "speaker": "老师",
    "text": "这就是我们矩形的判定方法呀。"
  },
  {
    "start": 1107.65,
    "end": 1110.93,
    "speaker": "老师",
    "text": "因此啊第三个命题也不对。"
  },
  {
    "start": 1111.13,
    "end": 1111.63,
    "speaker": "老师",
    "text": "好，"
  },
  {
    "start": 1111.63,
    "end": 1115.15,
    "speaker": "老师",
    "text": "我们再来看第四个命题对角线，"
  },
  {
    "start": 1115.15,
    "end": 1117.77,
    "speaker": "老师",
    "text": "互相垂直的矩形是正方形。"
  },
  {
    "start": 1118.13,
    "end": 1120.23,
    "speaker": "老师",
    "text": "同学们请看这里呢，"
  },
  {
    "start": 1120.23,
    "end": 1123.91,
    "speaker": "老师",
    "text": "已经告诉我们这个图形是矩形，"
  },
  {
    "start": 1123.93,
    "end": 1127.27,
    "speaker": "老师",
    "text": "并且它还说它的对角线互相垂直。"
  },
  {
    "start": 1127.63,
    "end": 1162.01,
    "speaker": "老师",
    "text": "我们知道矩形是特殊的平行四边形，"
  },
  {
    "start": 1162.23,
    "end": 1167.45,
    "speaker": "老师",
    "text": "而对角线互相垂直的平行四边形是菱形，"
  },
  {
    "start": 1167.45,
    "end": 1173.85,
    "speaker": "老师",
    "text": "因此这个图形既是矩形又是菱形，"
  },
  {
    "start": 1173.85,
    "end": 1179.51,
    "speaker": "老师",
    "text": "所以它是正方形没有问题。"
  },
  {
    "start": 1179.59,
    "end": 1180.11,
    "speaker": "老师",
    "text": "好，"
  },
  {
    "start": 1180.21,
    "end": 1186.07,
    "speaker": "老师",
    "text": "最后一个对角线互相垂直平分且相等的四边形是正方形。"
  },
  {
    "start": 1186.13,
    "end": 1192.02,
    "speaker": "老师",
    "text": "这里呢并没有说它是矩形还是菱形。"
  },
  {
    "start": 1192.06,
    "end": 1200.86,
    "speaker": "老师",
    "text": "我们进一步来看这里给的我们是关于对角线的信息。"
  },
  {
    "start": 1200.86,
    "end": 1206.3,
    "speaker": "老师",
    "text": "我们知道对角线互相平分，"
  },
  {
    "start": 1206.3,
    "end": 1211.6,
    "speaker": "老师",
    "text": "那它就应该是平行四边形，"
  },
  {
    "start": 1211.6,
    "end": 1212.92,
    "speaker": "老师",
    "text": "而垂直且平分，"
  },
  {
    "start": 1212.92,
    "end": 1215.2,
    "speaker": "老师",
    "text": "那它就应该是矩形。"
  },
  {
    "start": 1215.2,
    "end": 1216.84,
    "speaker": "老师",
    "text": "那么平分且相等呢，"
  },
  {
    "start": 1216.84,
    "end": 1218.77,
    "speaker": "老师",
    "text": "唉它就应该是矩形。"
  },
  {
    "start": 1218.77,
    "end": 1219.29,
    "speaker": "老师",
    "text": "因此，"
  },
  {
    "start": 1219.29,
    "end": 1225.58,
    "speaker": "老师",
    "text": "第五个命题我们同样既可以判定这个图形是菱形，"
  },
  {
    "start": 1225.58,
    "end": 1230.5,
    "speaker": "老师",
    "text": "又可以判定这个图形是矩形，"
  },
  {
    "start": 1230.5,
    "end": 1234.68,
    "speaker": "老师",
    "text": "因此它应该是正方形。"
  },
  {
    "start": 1234.68,
    "end": 1240.2,
    "speaker": "老师",
    "text": "所以第五个命题应该是正确的。"
  },
  {
    "start": 1240.56,
    "end": 1242.34,
    "speaker": "老师",
    "text": "好，"
  },
  {
    "start": 1242.36,
    "end": 1244.74,
    "speaker": "老师",
    "text": "那么接下来呀我们再来看这个问题。"
  },
  {
    "start": 1244.94,
    "end": 1250.0,
    "speaker": "老师",
    "text": "在四边形ABCD当中，"
  },
  {
    "start": 1250.0,
    "end": 1252.76,
    "speaker": "老师",
    "text": "o是对角线的交点，"
  },
  {
    "start": 1252.94,
    "end": 1257.02,
    "speaker": "老师",
    "text": "能判定这个四边形是正方形的。"
  },
  {
    "start": 1257.62,
    "end": 1261.97,
    "speaker": "老师",
    "text": "是这里呢老师给大家加大一点难度。"
  },
  {
    "start": 1262.01,
    "end": 1265.99,
    "speaker": "老师",
    "text": "我们呢不仅仅要找出哪一个选项，"
  },
  {
    "start": 1265.99,
    "end": 1268.03,
    "speaker": "老师",
    "text": "能判定正方形，"
  },
  {
    "start": 1268.03,
    "end": 1278.68,
    "speaker": "老师",
    "text": "其他的选项呢你们能通过其他选项判定这个图形是什么形状呢？"
  },
  {
    "start": 1280.03,
    "end": 1280.71,
    "speaker": "老师",
    "text": "来，"
  },
  {
    "start": 1280.81,
    "end": 1283.09,
    "speaker": "老师",
    "text": "先请大家自己思考一下。"
  },
  {
    "start": 1283.09,
    "end": 1283.72,
    "speaker": "老师",
    "text": "好了，"
  },
  {
    "start": 1284.45,
    "end": 1291.67,
    "speaker": "老师",
    "text": "同学们我们呢一起结合图形与选项来看一看a选项，"
  },
  {
    "start": 1291.67,
    "end": 1292.69,
    "speaker": "老师",
    "text": "AC等于BD,"
  },
  {
    "start": 1292.69,
    "end": 1295.67,
    "speaker": "老师",
    "text": "也就是对角线相等，"
  },
  {
    "start": 1295.67,
    "end": 1300.27,
    "speaker": "老师",
    "text": "并且还有AB平行于CDAB,"
  },
  {
    "start": 1300.75,
    "end": 1304.81,
    "speaker": "老师",
    "text": "等于CD一组对边平行且相等。"
  },
  {
    "start": 1304.81,
    "end": 1305.41,
    "speaker": "老师",
    "text": "哎，"
  },
  {
    "start": 1305.41,
    "end": 1306.69,
    "speaker": "老师",
    "text": "根据这两个，"
  },
  {
    "start": 1306.69,
    "end": 1311.69,
    "speaker": "老师",
    "text": "我们可以判断它是平行四边形，"
  },
  {
    "start": 1311.69,
    "end": 1318.39,
    "speaker": "老师",
    "text": "而对角线相等它是什么图形，"
  },
  {
    "start": 1318.65,
    "end": 1320.23,
    "speaker": "老师",
    "text": "没错矩形。"
  },
  {
    "start": 1320.27,
    "end": 1320.77,
    "speaker": "老师",
    "text": "好，"
  },
  {
    "start": 1320.79,
    "end": 1323.75,
    "speaker": "老师",
    "text": "我们再来看b选项，"
  },
  {
    "start": 1323.75,
    "end": 1325.95,
    "speaker": "老师",
    "text": "AD平行于BC."
  },
  {
    "start": 1325.95,
    "end": 1326.29,
    "speaker": "老师",
    "text": "好，"
  },
  {
    "start": 1326.79,
    "end": 1329.23,
    "speaker": "老师",
    "text": "一组对边平行，"
  },
  {
    "start": 1329.23,
    "end": 1333.87,
    "speaker": "老师",
    "text": "同时呢还有角DAB等于角DCB,"
  },
  {
    "start": 1334.29,
    "end": 1336.91,
    "speaker": "老师",
    "text": "我们呢进行标注。"
  },
  {
    "start": 1336.91,
    "end": 1337.87,
    "speaker": "老师",
    "text": "好，"
  },
  {
    "start": 1338.11,
    "end": 1341.75,
    "speaker": "老师",
    "text": "这两个角相等给了我们一组，"
  },
  {
    "start": 1341.75,
    "end": 1348.87,
    "speaker": "老师",
    "text": "对边平行一组对角相等，"
  },
  {
    "start": 1348.87,
    "end": 1355.65,
    "speaker": "老师",
    "text": "我们是不是无法判断它是一个什么四边形呢？"
  },
  {
    "start": 1356.11,
    "end": 1358.75,
    "speaker": "老师",
    "text": "同学们，"
  },
  {
    "start": 1359.51,
    "end": 1364.46,
    "speaker": "老师",
    "text": "我们再进一步来看，"
  },
  {
    "start": 1364.5,
    "end": 1368.14,
    "speaker": "老师",
    "text": "根据AD平行于BC,"
  },
  {
    "start": 1368.14,
    "end": 1373.01,
    "speaker": "老师",
    "text": "我们是不是可以得到两直线平行同旁内角互补。"
  },
  {
    "start": 1373.01,
    "end": 1407.62,
    "speaker": "老师",
    "text": "因此啊角BCD加角ADC应该等于一百八十度，"
  },
  {
    "start": 1407.62,
    "end": 1414.2,
    "speaker": "老师",
    "text": "而角ADAB呢又等于角BCD用一个等量代换，"
  },
  {
    "start": 1414.2,
    "end": 1420.42,
    "speaker": "老师",
    "text": "我们是不是可以得到角BAD加角ADC也等于一百八十度呢？"
  },
  {
    "start": 1420.48,
    "end": 1424.92,
    "speaker": "老师",
    "text": "用同旁内角互补两直线平行，"
  },
  {
    "start": 1425.12,
    "end": 1427.44,
    "speaker": "老师",
    "text": "所以就有了AB平行于CD."
  },
  {
    "start": 1427.44,
    "end": 1427.78,
    "speaker": "老师",
    "text": "哎，"
  },
  {
    "start": 1427.78,
    "end": 1433.76,
    "speaker": "老师",
    "text": "这个时候我是不是就有了两组对边平行，"
  },
  {
    "start": 1433.82,
    "end": 1438.5,
    "speaker": "老师",
    "text": "所以b选项我们可以判断它是一个平行四边形。"
  },
  {
    "start": 1438.52,
    "end": 1440.95,
    "speaker": "老师",
    "text": "再来看看c选项，"
  },
  {
    "start": 1440.95,
    "end": 1446.59,
    "speaker": "老师",
    "text": "OA等于OB等于OC等于OD好，"
  },
  {
    "start": 1446.65,
    "end": 1449.71,
    "speaker": "老师",
    "text": "也就是这四条都相等。"
  },
  {
    "start": 1449.71,
    "end": 1450.31,
    "speaker": "老师",
    "text": "哎，"
  },
  {
    "start": 1450.37,
    "end": 1452.15,
    "speaker": "老师",
    "text": "这四个相等的话，"
  },
  {
    "start": 1452.15,
    "end": 1456.01,
    "speaker": "老师",
    "text": "那是不是就说明了对角线互相平分，"
  },
  {
    "start": 1456.01,
    "end": 1458.33,
    "speaker": "老师",
    "text": "并且还相等呢？"
  },
  {
    "start": 1458.33,
    "end": 1463.65,
    "speaker": "老师",
    "text": "也就是说前面的这一个式子呢，"
  },
  {
    "start": 1463.65,
    "end": 1469.21,
    "speaker": "老师",
    "text": "我们可以判断四边形ABCD应该是一个矩形。"
  },
  {
    "start": 1469.21,
    "end": 1472.17,
    "speaker": "老师",
    "text": "而对角线AC又垂直于BD,"
  },
  {
    "start": 1472.17,
    "end": 1478.76,
    "speaker": "老师",
    "text": "也就是说它既是矩形，"
  },
  {
    "start": 1478.76,
    "end": 1480.68,
    "speaker": "老师",
    "text": "又是菱形。"
  },
  {
    "start": 1480.76,
    "end": 1485.54,
    "speaker": "老师",
    "text": "因此c选项应该可以判定四边形ABCD为正方形。"
  },
  {
    "start": 1485.54,
    "end": 1485.88,
    "speaker": "老师",
    "text": "好，"
  },
  {
    "start": 1486.64,
    "end": 1489.46,
    "speaker": "老师",
    "text": "最后我们再来看d选项，"
  },
  {
    "start": 1489.46,
    "end": 1492.94,
    "speaker": "老师",
    "text": "OA等于OCOB等于OD."
  },
  {
    "start": 1492.98,
    "end": 1493.46,
    "speaker": "老师",
    "text": "哎，"
  },
  {
    "start": 1494.04,
    "end": 1496.1,
    "speaker": "老师",
    "text": "对角线互相平分。"
  },
  {
    "start": 1496.2,
    "end": 1506.62,
    "speaker": "老师",
    "text": "那也就是说四边形ABCD首先它应该是一个平行四边形，"
  },
  {
    "start": 1506.62,
    "end": 1509.68,
    "speaker": "老师",
    "text": "AB等于BCAB等于BC,"
  },
  {
    "start": 1509.68,
    "end": 1512.24,
    "speaker": "老师",
    "text": "这是什么呢？"
  },
  {
    "start": 1512.36,
    "end": 1514.52,
    "speaker": "老师",
    "text": "一组邻边相等。"
  },
  {
    "start": 1514.52,
    "end": 1518.34,
    "speaker": "老师",
    "text": "所以四边形ABCD应该是菱形，"
  },
  {
    "start": 1518.62,
    "end": 1523.73,
    "speaker": "老师",
    "text": "同学们这道题目就应该选择的是c选项。"
  },
  {
    "start": 1523.73,
    "end": 1524.27,
    "speaker": "老师",
    "text": "好了，"
  },
  {
    "start": 1524.27,
    "end": 1530.35,
    "speaker": "老师",
    "text": "那么接下来呀我们再来看这样的一道题目，"
  },
  {
    "start": 1530.35,
    "end": 1531.79,
    "speaker": "老师",
    "text": "如图，"
  },
  {
    "start": 1531.79,
    "end": 1537.87,
    "speaker": "老师",
    "text": "在正方形ABCD当中，"
  },
  {
    "start": 1537.89,
    "end": 1544.15,
    "speaker": "老师",
    "text": "点EFMN分别在各边上，"
  },
  {
    "start": 1544.15,
    "end": 1550.97,
    "speaker": "老师",
    "text": "并且为各边的中点四边形EFMN是什么图形呢？"
  },
  {
    "start": 1550.97,
    "end": 1552.63,
    "speaker": "老师",
    "text": "为什么？"
  },
  {
    "start": 1552.63,
    "end": 1552.87,
    "speaker": "老师",
    "text": "好，"
  },
  {
    "start": 1552.87,
    "end": 1555.39,
    "speaker": "老师",
    "text": "同学们呢先自己思考完成这道题目。"
  },
  {
    "start": 1555.39,
    "end": 1582.87,
    "speaker": "老师",
    "text": "好了，"
  },
  {
    "start": 1582.87,
    "end": 1583.63,
    "speaker": "老师",
    "text": "同学们，"
  },
  {
    "start": 1583.63,
    "end": 1585.75,
    "speaker": "老师",
    "text": "我们呢一起来看看这道题目，"
  },
  {
    "start": 1585.75,
    "end": 1586.41,
    "speaker": "老师",
    "text": "题目，"
  },
  {
    "start": 1586.41,
    "end": 1590.76,
    "speaker": "老师",
    "text": "要求我们四边形EFMN是什么图形。"
  },
  {
    "start": 1590.76,
    "end": 1597.0,
    "speaker": "老师",
    "text": "并且呢还要我们说出理由来，"
  },
  {
    "start": 1597.1,
    "end": 1600.46,
    "speaker": "老师",
    "text": "这与我们普通的证明题呢不一样。"
  },
  {
    "start": 1600.46,
    "end": 1611.06,
    "speaker": "老师",
    "text": "我们首先要判断四边形EFMN它应该是一个怎样的形状。"
  },
  {
    "start": 1611.12,
    "end": 1611.52,
    "speaker": "老师",
    "text": "好，"
  },
  {
    "start": 1612.04,
    "end": 1649.48,
    "speaker": "老师",
    "text": "那么我们通过观察图形可以先进行一个预判。"
  },
  {
    "start": 1649.48,
    "end": 1652.56,
    "speaker": "老师",
    "text": "大家觉得EFMN是什么图形呢？"
  },
  {
    "start": 1652.56,
    "end": 1653.14,
    "speaker": "老师",
    "text": "没错，"
  },
  {
    "start": 1653.3,
    "end": 1654.16,
    "speaker": "老师",
    "text": "正方形。"
  },
  {
    "start": 1654.2,
    "end": 1661.09,
    "speaker": "老师",
    "text": "那么接下来啊我们就要找到支持我们预判的依据在哪里了。"
  },
  {
    "start": 1661.27,
    "end": 1662.65,
    "speaker": "老师",
    "text": "好，"
  },
  {
    "start": 1662.69,
    "end": 1664.45,
    "speaker": "老师",
    "text": "回到题目的条件当中，"
  },
  {
    "start": 1664.45,
    "end": 1668.07,
    "speaker": "老师",
    "text": "EFMN应该是各边的中点。"
  },
  {
    "start": 1668.07,
    "end": 1672.13,
    "speaker": "老师",
    "text": "而四边形ABCD它又是一个正方形，"
  },
  {
    "start": 1672.13,
    "end": 1676.4,
    "speaker": "老师",
    "text": "正方形我们知道它应该是四条边都相等，"
  },
  {
    "start": 1676.4,
    "end": 1678.79,
    "speaker": "老师",
    "text": "并且四个角都为九十度的。"
  },
  {
    "start": 1680.54,
    "end": 1686.52,
    "speaker": "老师",
    "text": "也就是说EFMN四个点将四条边分别分成了两个部分，"
  },
  {
    "start": 1686.68,
    "end": 1690.2,
    "speaker": "老师",
    "text": "并且这两个部分还是相等的。"
  },
  {
    "start": 1690.4,
    "end": 1692.04,
    "speaker": "老师",
    "text": "好，"
  },
  {
    "start": 1692.04,
    "end": 1699.8,
    "speaker": "老师",
    "text": "我们把相等的线段呢在图中进行标注。"
  },
  {
    "start": 1699.8,
    "end": 1709.06,
    "speaker": "老师",
    "text": "接下来刚才我们也说了角a角b角c角d应该都是什么角呢？"
  },
  {
    "start": 1709.08,
    "end": 1709.82,
    "speaker": "老师",
    "text": "没错，"
  },
  {
    "start": 1709.84,
    "end": 1711.4,
    "speaker": "老师",
    "text": "直角。"
  },
  {
    "start": 1711.8,
    "end": 1717.86,
    "speaker": "老师",
    "text": "这个时候我们就发现四个三角形，"
  },
  {
    "start": 1717.86,
    "end": 1723.23,
    "speaker": "老师",
    "text": "它们应该是什么三角形呢？"
  },
  {
    "start": 1723.23,
    "end": 1729.7,
    "speaker": "老师",
    "text": "等腰直角三角形并且呀每个三角形还都是全等的关系，"
  },
  {
    "start": 1729.72,
    "end": 1733.42,
    "speaker": "老师",
    "text": "所以我们就有对应边EF,"
  },
  {
    "start": 1733.42,
    "end": 1734.16,
    "speaker": "老师",
    "text": "等于FM,"
  },
  {
    "start": 1734.16,
    "end": 1736.9,
    "speaker": "老师",
    "text": "等于MN等于NE."
  },
  {
    "start": 1736.9,
    "end": 1749.01,
    "speaker": "老师",
    "text": "这个时候我们就不就首先判定出了四边形EFMN是菱形了吗？"
  },
  {
    "start": 1749.01,
    "end": 1749.37,
    "speaker": "老师",
    "text": "好，"
  },
  {
    "start": 1749.61,
    "end": 1751.75,
    "speaker": "老师",
    "text": "要判定它是正方形，"
  },
  {
    "start": 1751.75,
    "end": 1755.09,
    "speaker": "老师",
    "text": "那么我们还要判定它是矩形。"
  },
  {
    "start": 1755.09,
    "end": 1757.17,
    "speaker": "老师",
    "text": "同学们，"
  },
  {
    "start": 1757.19,
    "end": 1758.07,
    "speaker": "老师",
    "text": "请看，"
  },
  {
    "start": 1758.07,
    "end": 1759.39,
    "speaker": "老师",
    "text": "刚才我们说了，"
  },
  {
    "start": 1759.39,
    "end": 1766.97,
    "speaker": "老师",
    "text": "这每个小三角形都是等腰直角三角形，"
  },
  {
    "start": 1767.11,
    "end": 1771.93,
    "speaker": "老师",
    "text": "因此啊这些角应该是多少度呢？"
  },
  {
    "start": 1771.93,
    "end": 1773.77,
    "speaker": "老师",
    "text": "没错，"
  },
  {
    "start": 1773.77,
    "end": 1775.45,
    "speaker": "老师",
    "text": "四十五度，"
  },
  {
    "start": 1775.51,
    "end": 1778.91,
    "speaker": "老师",
    "text": "所以角NEF就应该是九十度。"
  },
  {
    "start": 1778.99,
    "end": 1779.31,
    "speaker": "老师",
    "text": "好，"
  },
  {
    "start": 1779.31,
    "end": 1812.16,
    "speaker": "老师",
    "text": "EMEFMN它是菱形，"
  },
  {
    "start": 1812.16,
    "end": 1814.68,
    "speaker": "老师",
    "text": "同时它还有角为九十度，"
  },
  {
    "start": 1814.68,
    "end": 1822.74,
    "speaker": "老师",
    "text": "那不就说明四边形EFMN为正方形了吗？"
  },
  {
    "start": 1822.74,
    "end": 1823.16,
    "speaker": "老师",
    "text": "好，"
  },
  {
    "start": 1823.16,
    "end": 1827.46,
    "speaker": "老师",
    "text": "这道题目完整的解题思路呢，"
  },
  {
    "start": 1827.46,
    "end": 1832.91,
    "speaker": "老师",
    "text": "同学们再来看一看好了同学们。"
  },
  {
    "start": 1832.91,
    "end": 1843.36,
    "speaker": "老师",
    "text": "那么现在啊老师对刚才的那道题目呢进行了一点小小的变化。"
  },
  {
    "start": 1843.36,
    "end": 1844.52,
    "speaker": "老师",
    "text": "大家请看，"
  },
  {
    "start": 1844.58,
    "end": 1847.78,
    "speaker": "老师",
    "text": "同样在正方形ABCD当中，"
  },
  {
    "start": 1848.06,
    "end": 1858.6,
    "speaker": "老师",
    "text": "点EFMN分别在各边上。"
  },
  {
    "start": 1859.32,
    "end": 1863.08,
    "speaker": "老师",
    "text": "但是它们现在不是终点了，"
  },
  {
    "start": 1863.18,
    "end": 1868.62,
    "speaker": "老师",
    "text": "老师给你们条件AE等于BF等于CM等于DN."
  },
  {
    "start": 1868.62,
    "end": 1874.66,
    "speaker": "老师",
    "text": "那么四边形EFMN还是正方形吗？"
  },
  {
    "start": 1874.66,
    "end": 1879.94,
    "speaker": "老师",
    "text": "为什么先请大家自己思考完成？"
  },
  {
    "start": 1880.18,
    "end": 1882.38,
    "speaker": "老师",
    "text": "好了，"
  },
  {
    "start": 1882.4,
    "end": 1887.54,
    "speaker": "老师",
    "text": "同学们我们一起啊回到这道题目上来。"
  },
  {
    "start": 1887.54,
    "end": 1895.12,
    "speaker": "老师",
    "text": "首先呢我们将已知条件在图形上进行标出。"
  },
  {
    "start": 1896.0,
    "end": 1900.62,
    "speaker": "老师",
    "text": "我们用黄色的点将相等的线段标记出来。"
  },
  {
    "start": 1900.62,
    "end": 1904.36,
    "speaker": "老师",
    "text": "因为四边形ABCD是正方形，"
  },
  {
    "start": 1904.36,
    "end": 1909.74,
    "speaker": "老师",
    "text": "所以它的四条边应该是没错相等的。"
  },
  {
    "start": 1909.74,
    "end": 1913.42,
    "speaker": "老师",
    "text": "我们用每一条边减去标记为黄色的这个线段。"
  },
  {
    "start": 1913.42,
    "end": 1913.72,
    "speaker": "老师",
    "text": "好，"
  },
  {
    "start": 1913.72,
    "end": 1916.44,
    "speaker": "老师",
    "text": "剩下的部分是不是也相等呢？"
  },
  {
    "start": 1916.44,
    "end": 1922.31,
    "speaker": "老师",
    "text": "同样我们呢用红色的点将相等的线段标记出来。"
  },
  {
    "start": 1922.33,
    "end": 1931.49,
    "speaker": "老师",
    "text": "那我们又知道正方形的四个角角a角b角c角d应该是相等的。"
  },
  {
    "start": 1931.49,
    "end": 1935.13,
    "speaker": "老师",
    "text": "这个时候我就发现三角形AEN,"
  },
  {
    "start": 1935.17,
    "end": 1940.45,
    "speaker": "老师",
    "text": "三角形BFE、三角形CMF以及三角形DNM,"
  },
  {
    "start": 1940.45,
    "end": 1943.7,
    "speaker": "老师",
    "text": "它们应该是全等的关系，"
  },
  {
    "start": 1943.74,
    "end": 1944.44,
    "speaker": "老师",
    "text": "为什么呢？"
  },
  {
    "start": 1944.44,
    "end": 1945.52,
    "speaker": "老师",
    "text": "边角边呢？"
  },
  {
    "start": 1945.56,
    "end": 1945.84,
    "speaker": "老师",
    "text": "好，"
  },
  {
    "start": 1945.84,
    "end": 1949.46,
    "speaker": "老师",
    "text": "既然这四个三角形全等了，"
  },
  {
    "start": 1949.48,
    "end": 1954.06,
    "speaker": "老师",
    "text": "那就有对应边EF等于FM等于MN等于NE."
  },
  {
    "start": 1954.28,
    "end": 1958.96,
    "speaker": "老师",
    "text": "首先我判断出了四边形EFMN应该是菱形。"
  },
  {
    "start": 1958.96,
    "end": 1966.08,
    "speaker": "老师",
    "text": "接下来呢我们还要判断这在这个四边形EFM当中有一个角为直角啊。"
  },
  {
    "start": 1966.08,
    "end": 1966.38,
    "speaker": "老师",
    "text": "好，"
  },
  {
    "start": 1966.38,
    "end": 1967.82,
    "speaker": "老师",
    "text": "同学们请看。"
  },
  {
    "start": 1967.82,
    "end": 1973.08,
    "speaker": "老师",
    "text": "既然我们刚才已经说了三角形AEN全等于三角形BFE,"
  },
  {
    "start": 1973.08,
    "end": 1976.68,
    "speaker": "老师",
    "text": "从而我们可以得到对应角是相等的，"
  },
  {
    "start": 1976.68,
    "end": 1979.46,
    "speaker": "老师",
    "text": "而角ANE加角AEN,"
  },
  {
    "start": 1979.46,
    "end": 1979.78,
    "speaker": "老师",
    "text": "哎，"
  },
  {
    "start": 1979.78,
    "end": 1980.92,
    "speaker": "老师",
    "text": "是多少度呢？"
  },
  {
    "start": 1980.92,
    "end": 1981.84,
    "speaker": "老师",
    "text": "没错，"
  },
  {
    "start": 1981.86,
    "end": 1985.71,
    "speaker": "老师",
    "text": "九十度用一个等量代换，"
  },
  {
    "start": 1985.71,
    "end": 1992.36,
    "speaker": "老师",
    "text": "我们就可以得到角BEF加角AEN也等于九十度，"
  },
  {
    "start": 1992.36,
    "end": 1995.44,
    "speaker": "老师",
    "text": "从而可以得出角NEF应该为九十度。"
  },
  {
    "start": 1995.44,
    "end": 1999.79,
    "speaker": "老师",
    "text": "也就是说在这个菱形EFMN当中，"
  },
  {
    "start": 2000.23,
    "end": 2002.49,
    "speaker": "老师",
    "text": "有一个角为直角，"
  },
  {
    "start": 2002.49,
    "end": 2005.99,
    "speaker": "老师",
    "text": "所以四边形EFMN应该是没错正方形。"
  },
  {
    "start": 2005.99,
    "end": 2006.41,
    "speaker": "老师",
    "text": "好，"
  },
  {
    "start": 2006.41,
    "end": 2012.7,
    "speaker": "老师",
    "text": "我们呢再把这道题的完整证明思路来进行一个回顾。"
  },
  {
    "start": 2012.7,
    "end": 2013.08,
    "speaker": "老师",
    "text": "好，"
  },
  {
    "start": 2013.08,
    "end": 2013.94,
    "speaker": "老师",
    "text": "同学们，"
  },
  {
    "start": 2013.94,
    "end": 2020.26,
    "speaker": "老师",
    "text": "那如果老师再对刚才的图形进行一个变化，"
  },
  {
    "start": 2020.26,
    "end": 2024.9,
    "speaker": "老师",
    "text": "现在点EFMN不在正方形ABCD的各边上。"
  },
  {
    "start": 2024.9,
    "end": 2028.29,
    "speaker": "老师",
    "text": "而在各边的延长线上，"
  },
  {
    "start": 2028.29,
    "end": 2029.31,
    "speaker": "老师",
    "text": "同学们看图，"
  },
  {
    "start": 2029.37,
    "end": 2031.79,
    "speaker": "老师",
    "text": "我同时呢给你AE等于BF,"
  },
  {
    "start": 2032.33,
    "end": 2034.05,
    "speaker": "老师",
    "text": "等于CM等于DN."
  },
  {
    "start": 2034.05,
    "end": 2035.88,
    "speaker": "老师",
    "text": "你能够判断四边形，"
  },
  {
    "start": 2036.96,
    "end": 2038.96,
    "speaker": "老师",
    "text": "EFMN是什么四边形吗？"
  },
  {
    "start": 2039.22,
    "end": 2041.26,
    "speaker": "老师",
    "text": "其实啊道理跟刚才是一样的，"
  },
  {
    "start": 2041.26,
    "end": 2052.98,
    "speaker": "老师",
    "text": "我同样可以证明四个三角形AEF、 BFM、 CMN以及DNE是全等的关系。"
  },
  {
    "start": 2053.08,
    "end": 2057.92,
    "speaker": "老师",
    "text": "先证明四条对应边相等得出四边形是菱形之后呢，"
  },
  {
    "start": 2057.92,
    "end": 2062.78,
    "speaker": "老师",
    "text": "我再证明在这个菱形当中有一个角为九十度，"
  },
  {
    "start": 2062.78,
    "end": 2064.74,
    "speaker": "老师",
    "text": "同样可以得出四边形。"
  },
  {
    "start": 2064.26,
    "end": 2064.74,
    "speaker": "老师",
    "text": "Efmn是正方形，"
  },
  {
    "start": 2064.26,
    "end": 2064.74,
    "speaker": "老师",
    "text": "那老师再进行变化。"
  },
  {
    "start": 2064.26,
    "end": 2064.74,
    "speaker": "老师",
    "text": "如果EFMN现在到了正方形的对角线上，"
  },
  {
    "start": 2064.26,
    "end": 2064.74,
    "speaker": "老师",
    "text": "同样给你AE等于BF,"
  },
  {
    "start": 2064.26,
    "end": 2064.74,
    "speaker": "老师",
    "text": "等于CM等于DN呢？"
  },
  {
    "start": 2064.26,
    "end": 2064.74,
    "speaker": "老师",
    "text": "这个时候EFMN还是正方形吗？"
  },
  {
    "start": 2064.26,
    "end": 2064.74,
    "speaker": "老师",
    "text": "其实啊道理是一样的。"
  },
  {
    "start": 2064.26,
    "end": 2064.74,
    "speaker": "老师",
    "text": "那么最后的这两道题目呢，"
  },
  {
    "start": 2064.26,
    "end": 2064.74,
    "speaker": "老师",
    "text": "就留给同学们自己在课后进行完整的书写。"
  },
  {
    "start": 2064.26,
    "end": 2064.74,
    "speaker": "老师",
    "text": "好，"
  },
  {
    "start": 2064.26,
    "end": 2064.74,
    "speaker": "老师",
    "text": "同学们呢今天的时间呢过得非常的快，"
  },
  {
    "start": 2064.26,
    "end": 2064.74,
    "speaker": "老师",
    "text": "那么在课程的最后我们还是要来一起回顾总结一下这节课我们都学习了哪些知识呢？"
  },
  {
    "start": 2064.26,
    "end": 2064.74,
    "speaker": "老师",
    "text": "这节课我们先从正方形的定义开始之后呢，"
  },
  {
    "start": 2064.26,
    "end": 2064.74,
    "speaker": "老师",
    "text": "归纳了四边形、平行四边形、矩形、菱形以及正方形之间的关系。"
  },
  {
    "start": 2064.26,
    "end": 2064.74,
    "speaker": "老师",
    "text": "再根据这些图形之间的关系，"
  },
  {
    "start": 2064.26,
    "end": 2064.74,
    "speaker": "老师",
    "text": "得出了正方形的性质以及判定之后呢，"
  },
  {
    "start": 2064.26,
    "end": 2064.74,
    "speaker": "老师",
    "text": "再对我们所学的知识进行了一个运用。"
  },
  {
    "start": 2064.26,
    "end": 2064.74,
    "speaker": "老师",
    "text": "那么对于今天的学习，"
  },
  {
    "start": 2064.26,
    "end": 2064.74,
    "speaker": "老师",
    "text": "同学们又有哪些数学感悟吗？"
  },
  {
    "start": 2064.26,
    "end": 2064.74,
    "speaker": "老师",
    "text": "其实啊今天我们还是进行了一个类比学习，"
  },
  {
    "start": 2064.26,
    "end": 2064.74,
    "speaker": "老师",
    "text": "类比了平行四边形矩形以及菱形的学习方法，"
  },
  {
    "start": 2064.26,
    "end": 2064.74,
    "speaker": "老师",
    "text": "并且将这些图形的性质转移到了正方形上来，"
  },
  {
    "start": 2064.26,
    "end": 2064.74,
    "speaker": "老师",
    "text": "实现了知识的迁移。"
  },
  {
    "start": 2064.26,
    "end": 2064.74,
    "speaker": "老师",
    "text": "另外呢在这里老师还想回答大家一个疑问，"
  },
  {
    "start": 2064.26,
    "end": 2064.74,
    "speaker": "老师",
    "text": "总有同学认为数学非常的难学，"
  },
  {
    "start": 2064.26,
    "end": 2064.74,
    "speaker": "老师",
    "text": "做了很多题目，"
  },
  {
    "start": 2064.26,
    "end": 2064.74,
    "speaker": "老师",
    "text": "怎么也提高不了自己的成绩。"
  },
  {
    "start": 2064.26,
    "end": 2064.74,
    "speaker": "老师",
    "text": "而且呀数学怎么会有那么多各种各样的题目呢？"
  },
  {
    "start": 2064.26,
    "end": 2064.74,
    "speaker": "老师",
    "text": "其实啊这很大的一个原因就是因为数学它会变。"
  },
  {
    "start": 2064.26,
    "end": 2064.74,
    "speaker": "老师",
    "text": "今天老师就给大家展示了数学之变，"
  },
  {
    "start": 2064.26,
    "end": 2064.74,
    "speaker": "老师",
    "text": "这冰山的一角从一道题目出发，"
  },
  {
    "start": 2064.26,
    "end": 2064.74,
    "speaker": "老师",
    "text": "一下子呢就变出了三道题目，"
  },
  {
    "start": 2064.26,
    "end": 2064.74,
    "speaker": "老师",
    "text": "甚至呢还可以变得更多。"
  },
  {
    "start": 2064.26,
    "end": 2064.74,
    "speaker": "老师",
    "text": "但是我们发现只要我们掌握了正方形的判定，"
  },
  {
    "start": 2064.26,
    "end": 2064.74,
    "speaker": "老师",
    "text": "紧紧的抓住正方形的判定，"
  },
  {
    "start": 2064.26,
    "end": 2064.74,
    "speaker": "老师",
    "text": "那么这些问题就都可以迎刃而解。"
  },
  {
    "start": 2064.26,
    "end": 2064.74,
    "speaker": "老师",
    "text": "也就是说我们呢往往可以用一个办法或者是类似的办法去解决一类问题。"
  },
  {
    "start": 2064.26,
    "end": 2064.74,
    "speaker": "老师",
    "text": "这个呢也就是我们所说的万变不离其宗，"
  },
  {
    "start": 2064.26,
    "end": 2064.74,
    "speaker": "老师",
    "text": "只要你能够抓住这个宗啊，"
  },
  {
    "start": 2064.26,
    "end": 2064.74,
    "speaker": "老师",
    "text": "那么你就能够做到触类旁通。"
  },
  {
    "start": 2064.26,
    "end": 2064.74,
    "speaker": "老师",
    "text": "好了，"
  },
  {
    "start": 2064.26,
    "end": 2064.74,
    "speaker": "老师",
    "text": "那么对于今天的学习，"
  },
  {
    "start": 2064.26,
    "end": 2064.74,
    "speaker": "老师",
    "text": "同学们还有哪些质疑和发现吗？"
  },
  {
    "start": 2064.26,
    "end": 2064.74,
    "speaker": "老师",
    "text": "欢迎大家呀通过邮件的方式来与老师交流学习呢，"
  },
  {
    "start": 2064.26,
    "end": 2064.74,
    "speaker": "老师",
    "text": "并不仅仅发生在课堂，"
  },
  {
    "start": 2064.26,
    "end": 2064.74,
    "speaker": "老师",
    "text": "我们的课后作业便是学习的延续与深化，"
  },
  {
    "start": 2064.26,
    "end": 2064.74,
    "speaker": "老师",
    "text": "希望大家能够认真自主的完成今天的课后作业。"
  },
  {
    "start": 2064.26,
    "end": 2064.74,
    "speaker": "老师",
    "text": "同学们下一节课呢将由贺老师带着大家一起进行实验和探究。"
  },
  {
    "start": 2064.26,
    "end": 2064.74,
    "speaker": "老师",
    "text": "请同学们呢提前准备好需要用的学习用具。"
  },
  {
    "start": 2064.26,
    "end": 2064.74,
    "speaker": "老师",
    "text": "好了，"
  },
  {
    "start": 2064.26,
    "end": 2064.74,
    "speaker": "老师",
    "text": "那么这节课我们就上到这里，"
  },
  {
    "start": 2064.26,
    "end": 2064.74,
    "speaker": "老师",
    "text": "同学们再见。"
  }
]